{
  "data": [
    {
      "id": "1",
      "type": "platform",
      "category": "Academy",
      "categories": [
        { "id": 1, "name" : "IT", "icon" : "" },
        { "id": 2, "name" : "Web3", "icon" : "" }
      ],
      "banner": "Grasp-Banner.png",
      "image": "Grasp-Icon.png",
      "title": "Grasp Academy",
      "description":
        "Grasp Academy is the premier educational content platform where educators and creators can share their work and earn on EDU Chain. Powered by Open Campus, the Grasp web3 platform integrates EduFi, enabling users to learn, earn, and be rewarded for academic excellence.",
      "contact": "Craig Moss",
      "email": "graspcampus@gmail.com",
      "phone": "082 229 2839",
      "city": "Cape Town",
      "country": "South Africa",
      "website": { "title": "www.grasp.academy", "url": "http://grasp.academy/", "alt": "Grasp Academy", "icon": "website" },
      "twitter": { "title": "@GraspAcademy", "url": "https://twitter.com/GraspAcademy", "alt": "Twitter Username", "icon": "twitter" },
      "discord": { "title": "", "url": "", "alt": "Dicord Username", "icon": "discord" },
      "telegram": { "title": "", "url": "", "alt": "Telegram Username", "icon": "telegram" },
      "linkedin": { "title": "", "url": "", "alt": "LinkedIn Profile", "icon": "linkedin" },
      "created_date": "15/07/2024",
      "updated_date": "17/07/2024",
      "enabled": true,
      "verified": false,
      "blocked": false
    }
  ]
}
